juicewrld_api_wrapper/__init__.py
juicewrld_api_wrapper/client.py
juicewrld_api_wrapper/examples.py
juicewrld_api_wrapper/exceptions.py
juicewrld_api_wrapper/models.py
juicewrld_api_wrapper/test_wrapper.py
juicewrld_api_wrapper-1.0.4.dist-info/licenses/LICENSE
juicewrld_api_wrapper-1.0.4.dist-info/METADATA
juicewrld_api_wrapper-1.0.4.dist-info/WHEEL
juicewrld_api_wrapper-1.0.4.dist-info/top_level.txt
juicewrld_api_wrapper-1.0.4.dist-info/RECORD
