Metadata-Version: 2.4
Name: juicewrld-api-wrapper
Version: 1.0.4
Summary: A comprehensive Python wrapper for the Juice WRLD API
Home-page: https://github.com/HackinHood/juicewrld-api-wrapper
Author: Juice WRLD API Wrapper
Author-email: Juice WRLD API Wrapper <support@juicewrldapi.com>
Maintainer-email: Juice WRLD API Wrapper <support@juicewrldapi.com>
License-Expression: MIT
Project-URL: Homepage, https://github.com/HackinHood/juicewrld-api-wrapper
Project-URL: Documentation, https://github.com/HackinHood/juicewrld-api-wrapper#readme
Project-URL: Repository, https://github.com/HackinHood/juicewrld-api-wrapper
Project-URL: Bug Tracker, https://github.com/HackinHood/juicewrld-api-wrapper/issues
Project-URL: Source Code, https://github.com/HackinHood/juicewrld-api-wrapper
Keywords: juice wrld,api,wrapper,music,discography,python
Classifier: Development Status :: 5 - Production/Stable
Classifier: Intended Audience :: Developers
Classifier: Operating System :: OS Independent
Classifier: Programming Language :: Python :: 3
Classifier: Programming Language :: Python :: 3.7
Classifier: Programming Language :: Python :: 3.8
Classifier: Programming Language :: Python :: 3.9
Classifier: Programming Language :: Python :: 3.10
Classifier: Programming Language :: Python :: 3.11
Classifier: Programming Language :: Python :: 3.12
Classifier: Topic :: Software Development :: Libraries :: Python Modules
Classifier: Topic :: Multimedia :: Sound/Audio
Classifier: Topic :: Internet :: WWW/HTTP :: Dynamic Content
Classifier: Topic :: Internet :: WWW/HTTP :: HTTP Servers
Requires-Python: >=3.7
License-File: LICENSE
Requires-Dist: requests>=2.28.0
Provides-Extra: dev
Requires-Dist: pytest>=6.0; extra == "dev"
Requires-Dist: pytest-cov>=2.0; extra == "dev"
Requires-Dist: black>=21.0; extra == "dev"
Requires-Dist: flake8>=3.8; extra == "dev"
Requires-Dist: mypy>=0.800; extra == "dev"
Requires-Dist: twine>=4.0; extra == "dev"
Requires-Dist: build>=0.10; extra == "dev"
Dynamic: author
Dynamic: home-page
Dynamic: license-file
Dynamic: requires-python
